jitcxde_common/__init__.py
jitcxde_common/_jitcxde.py
jitcxde_common/check.py
jitcxde_common/code.py
jitcxde_common/helpers.py
jitcxde_common/modules.py
jitcxde_common/modules_33.py
jitcxde_common/modules_35.py
jitcxde_common/numerical.py
jitcxde_common/strings.py
jitcxde_common/symbolic.py
jitcxde_common/transversal.py
jitcxde_common/version.py
jitcxde_common-1.5.6.dist-info/licenses/LICENSE
jitcxde_common-1.5.6.dist-info/METADATA
jitcxde_common-1.5.6.dist-info/WHEEL
jitcxde_common-1.5.6.dist-info/top_level.txt
jitcxde_common-1.5.6.dist-info/RECORD
